nba_video_generator/search.py
nba_video_generator/src/get_box_scores.py
nba_video_generator/src/get_player_urls.py
nba_video_generator/src/get_videos.py
nba_video_generator-2.0.21.dist-info/licenses/LICENSE
nba_video_generator-2.0.21.dist-info/METADATA
nba_video_generator-2.0.21.dist-info/WHEEL
nba_video_generator-2.0.21.dist-info/top_level.txt
nba_video_generator-2.0.21.dist-info/RECORD
