Metadata-Version: 2.4
Name: nba-video-generator
Version: 2.0.21
Summary: Generates video highlights for an NBA player.
Author-email: Ronen Huang <ronenhuang24@gmail.com>
Project-URL: Homepage, https://github.com/ronenh24/nba_video_generator
Project-URL: Issues, https://github.com/ronenh24/nba_video_generator/issues
Classifier: Programming Language :: Python :: 3
Classifier: Operating System :: OS Independent
Classifier: License :: OSI Approved :: Apache Software License
Requires-Python: >=3.9
License-File: LICENSE
Requires-Dist: moviepy
Requires-Dist: selenium
Requires-Dist: Unidecode
Dynamic: license-file
